aiosendgrid/__init__.py
aiosendgrid/auth.py
aiosendgrid/client.py
aiosendgrid/constants.py
aiosendgrid-0.1.0.dist-info/WHEEL
aiosendgrid-0.1.0.dist-info/METADATA
aiosendgrid-0.1.0.dist-info/RECORD
