Metadata-Version: 2.1
Name: aiosendgrid
Version: 0.1.0
Summary: Async SendGrid client based on httpx
Home-page: https://github.com/kozlek/aiosendgrid
Author: Thomas BERDY
Author-email: thomas.berdy@outlook.com
Requires-Python: >=3.9,<4.0
Classifier: Programming Language :: Python :: 3
Classifier: Programming Language :: Python :: 3.10
Classifier: Programming Language :: Python :: 3.9
Provides-Extra: helpers
Requires-Dist: httpx[http2] (>=0.22.0)
Requires-Dist: sendgrid (>=6.9.6); extra == "helpers"
Project-URL: Repository, https://github.com/kozlek/aiosendgrid
